EventManager/__init__.py
EventManager/event_manager.py
EventManager/internal_event_manager.py
EventManager/compressors/__init__.py
EventManager/compressors/compressors.py
EventManager/compressors/gzip_compressor.py
EventManager/compressors/zip_compressor.py
EventManager/filehandlers/__init__.py
EventManager/filehandlers/log_handler.py
EventManager/filehandlers/config/__init__.py
EventManager/filehandlers/config/config.py
EventManager/filehandlers/config/config_event.py
EventManager/filehandlers/config/config_internal_events.py
EventManager/filehandlers/config/config_log_file.py
EventManager/filehandlers/config/config_log_rotate.py
EventManager/filehandlers/config/helper.py
EventManager/filehandlers/config/output_entry.py
EventManager/filehandlers/config/processor_entry.py
EventManager/filehandlers/config/regex_entry.py
EventManager/filehandlers/config/socket_entry.py
EventManager/formatters/__init__.py
EventManager/formatters/csv_formatter.py
EventManager/formatters/default_formatter.py
EventManager/formatters/event_creator.py
EventManager/formatters/event_formatter.py
EventManager/formatters/formatter_strategy.py
EventManager/formatters/json_formatter.py
EventManager/formatters/key_value_formatter.py
EventManager/formatters/key_value_wrapper.py
EventManager/formatters/xml_formatter.py
EventManager/internal/__init__.py
EventManager/internal/event_metadata_builder.py
EventManager/internal/managerbase.py
EventManager/internal/output_helper.py
EventManager/internal/processor_helper.py
EventManager/internal/thread_helper.py
EventManager/outputs/Batch.py
EventManager/outputs/DefaultOutput.py
EventManager/outputs/Output.py
EventManager/outputs/__init__.py
EventManager/outputs/logoutput.py
EventManager/outputs/printoutput.py
EventManager/outputs/socketoutput.py
EventManager/processors/Processor.py
EventManager/processors/__init__.py
EventManager/processors/enrichingprocessor.py
EventManager/processors/filterprocessor.py
EventManager/processors/maskipv4address.py
eventmanagerpy-1.0.0.dist-info/METADATA
eventmanagerpy-1.0.0.dist-info/WHEEL
eventmanagerpy-1.0.0.dist-info/top_level.txt
eventmanagerpy-1.0.0.dist-info/RECORD
