Metadata-Version: 2.4
Name: EventManagerPy
Version: 1.0.0
Summary: EventManager is a logging module designed to be used in a multi-threaded environment
Home-page: https://github.com/TheBloodyAmateur/EventManagerPython
Author: Botan Celik
Author-email: botan.celik@icloud.com
Classifier: Programming Language :: Python :: 3
Classifier: License :: OSI Approved :: MIT License
Classifier: Operating System :: OS Independent
Requires-Python: >=3.13
Requires-Dist: setuptools~=78.1.0
Requires-Dist: psutil~=7.0.0
Requires-Dist: pydantic~=2.11.3
Requires-Dist: atomics~=1.0.3
Requires-Dist: urllib3~=2.4.0
Requires-Dist: sphinx_rtd_theme~=1.2.0
Dynamic: author
Dynamic: author-email
Dynamic: classifier
Dynamic: description
Dynamic: description-content-type
Dynamic: home-page
Dynamic: requires-dist
Dynamic: requires-python
Dynamic: summary
